{
    "static_data": {
        "total_time": 120,
        "service_time": 1,
        "urgency_std": 0.97,
        "number_of_vehicles": 2,
        "max_vehicle_capacity": 4,
        "urgency_mean": 2.44,
        "dynamism": 0.65
    },
    "requests": [
        {
            "service_type": "drop",
            "desired_time": 23,
            "known_time": 18.41,
            "max_ride_time": 100,
            "max_wait_time": 10,
            "service_point_x": -2.7,
            "service_point_y": 4.0
        },
        {
            "service_type": "pick",
            "desired_time": 32,
            "known_time": 29.55,
            "max_ride_time": 100,
            "max_wait_time": 10,
            "service_point_x": -0.7,
            "service_point_y": 4.9
        },
        {
            "service_type": "drop",
            "desired_time": 46,
            "known_time": 43.96,
            "max_ride_time": 100,
            "max_wait_time": 10,
            "service_point_x": -0.1,
            "service_point_y": -0.7
        },
        {
            "service_type": "pick",
            "desired_time": 70,
            "known_time": 68.39,
            "max_ride_time": 100,
            "max_wait_time": 10,
            "service_point_x": -1.6,
            "service_point_y": -3.5
        },
        {
            "service_type": "drop",
            "desired_time": 76,
            "known_time": 73.98,
            "max_ride_time": 100,
            "max_wait_time": 10,
            "service_point_x": -4.5,
            "service_point_y": 0.1
        },
        {
            "service_type": "drop",
            "desired_time": 101,
            "known_time": 98.16,
            "max_ride_time": 100,
            "max_wait_time": 10,
            "service_point_x": -0.1,
            "service_point_y": 2.4
        },
        {
            "service_type": "pick",
            "desired_time": 115,
            "known_time": 113.48,
            "max_ride_time": 100,
            "max_wait_time": 10,
            "service_point_x": 1.8,
            "service_point_y": 6.3
        }
    ]
}