{
    "static_data": {
        "total_time": 120,
        "urgency_mean": 1.68,
        "urgency_std": 1.07,
        "number_of_vehicles": 2,
        "max_vehicle_capacity": 4,
        "service_time": 1,
        "priori_ratio": 0.5,
        "dp_ratio": 0.5,
        "dynamism": 0.39
    },
    "requests": [
        {
            "service_type": "drop",
            "desired_time": 29,
            "known_time": 28.72,
            "max_ride_time": 100,
            "max_wait_time": 10,
            "service_point_x": -0.5,
            "service_point_y": 3.8
        },
        {
            "service_type": "pick",
            "desired_time": 56,
            "known_time": 54.39,
            "max_ride_time": 100,
            "max_wait_time": 10,
            "service_point_x": -1.6,
            "service_point_y": -2.4
        },
        {
            "service_type": "drop",
            "desired_time": 65,
            "known_time": 61.99,
            "max_ride_time": 100,
            "max_wait_time": 10,
            "service_point_x": -1.0,
            "service_point_y": -0.3
        },
        {
            "service_type": "pick",
            "desired_time": 102,
            "known_time": 99.26,
            "max_ride_time": 100,
            "max_wait_time": 10,
            "service_point_x": -5.7,
            "service_point_y": 4.0
        },
        {
            "service_type": "drop",
            "desired_time": 102,
            "known_time": 101.25,
            "max_ride_time": 100,
            "max_wait_time": 10,
            "service_point_x": 2.7,
            "service_point_y": -3.2
        }
    ]
}